YouSanAiShijueSuanfaGongchengshiChengchangZhidaoShouce20190812/README.md
YouSanAiShijueSuanfaGongchengshiChengchangZhidaoShouce20190812/__init__.py
YouSanAiShijueSuanfaGongchengshiChengchangZhidaoShouce20190812/__main__.py
YouSanAiShijueSuanfaGongchengshiChengchangZhidaoShouce20190812/file.pdf
YouSanAiShijueSuanfaGongchengshiChengchangZhidaoShouce20190812/index.html
you_san_ai_shijue_suanfa_gongchengshi_chengchang_zhidao_shouce_20190812-2024.3.5.0.dist-info/METADATA
you_san_ai_shijue_suanfa_gongchengshi_chengchang_zhidao_shouce_20190812-2024.3.5.0.dist-info/WHEEL
you_san_ai_shijue_suanfa_gongchengshi_chengchang_zhidao_shouce_20190812-2024.3.5.0.dist-info/entry_points.txt
you_san_ai_shijue_suanfa_gongchengshi_chengchang_zhidao_shouce_20190812-2024.3.5.0.dist-info/top_level.txt
you_san_ai_shijue_suanfa_gongchengshi_chengchang_zhidao_shouce_20190812-2024.3.5.0.dist-info/RECORD
